gviz_api.py
gviz_api-1.10.0.dist-info/METADATA
gviz_api-1.10.0.dist-info/WHEEL
gviz_api-1.10.0.dist-info/top_level.txt
gviz_api-1.10.0.dist-info/RECORD
